web_fetch/__init__.py
web_fetch/random_agent.py
web_fetch/web_fetch.py
web_fetch-0.1.1.3.dist-info/METADATA
web_fetch-0.1.1.3.dist-info/WHEEL
web_fetch-0.1.1.3.dist-info/top_level.txt
web_fetch-0.1.1.3.dist-info/RECORD
