Metadata-Version: 2.1
Name: web_fetch
Version: 0.1.1.3
Summary: A package to fetch web resources and cache HTML content.
Home-page: https://github.com/li-xiu-qi/web_fetch
Author: li-xiu-qi
Author-email: lixiuqixiaoke@qq.com
Classifier: Programming Language :: Python :: 3
Classifier: License :: OSI Approved :: MIT License
Classifier: Operating System :: OS Independent
Requires-Python: >=3.7
Requires-Dist: requests
Requires-Dist: beautifulsoup4
Requires-Dist: diskcache
Requires-Dist: python-dotenv
Requires-Dist: htmldate
Requires-Dist: pydantic
